Workbook

Sheet Documentation
A1: Green View Camping Supplies
A3: Author | B3: Wynton Karls
A4: Date | B4: 45717
A5: Purpose | B5: To estimate the next five years of financial statements for Green View Camping Supplies

Sheet Income Statement
A1: Green View Camping Supplies
A2: Income Statement
A4: Income | B4: Year 1 | C4: Year 2 | D4: Year 3 | E4: Year 4 | F4: Year 5 | H4: Estimated Tax Liability | I4: 0.32
A5: Sales | B5: 1200000 | C5: 1500000 | D5: 1800000 | E5: 2200000 | F5: 2500000
A6: Cost of Marketing | B6: 300000 | C6: 340000 | D6: 380000 | E6: 440000 | F6: 500000
A7: Cost of R&D | B7: 180000 | C7: 220000 | D7: 260000 | E7: 300000 | F7: 350000
A8: GROSS PROFIT | B8: =B5-(B6+B7) -> 720000 | C8: =C5-(C6+C7) -> 940000 | D8: =D5-(D6+D7) -> 1160000 | E8: =E5-(E6+E7) -> 1460000 | F8: =F5-(F6+F7) -> 1650000
A10: Expenses | B10: Year 1 | C10: Year 2 | D10: Year 3 | E10: Year 4 | F10: Year 5
A11: Payroll | B11: 420000 | C11: 450000 | D11: 480000 | E11: 540000 | F11: 650000
A12: Utilities | B12: 65000 | C12: 70000 | D12: 75000 | E12: 80000 | F12: 90000
A13: Licensing | B13: 35000 | C13: 35000 | D13: 40000 | E13: 40000 | F13: 45000
A14: Occupancy Costs | B14: 60000 | C14: 65000 | D14: 70000 | E14: 75000 | F14: 80000
A15: Insurance | B15: 25000 | C15: 28000 | D15: 31000 | E15: 35000 | F15: 40000
A16: Miscellaneous Expenses | B16: 20000 | C16: 23000 | D16: 26000 | E16: 30000 | F16: 35000
A17: TOTAL EXPENSES | B17: =SUM(B11:B16) -> 625000 | C17: =SUM(C11:C16) -> 671000 | D17: =SUM(D11:D16) -> 722000 | E17: =SUM(E11:E16) -> 800000 | F17: =SUM(F11:F16) -> 940000
A19: Earnings | B19: Year 1 | C19: Year 2 | D19: Year 3 | E19: Year 4 | F19: Year 5
A20: Initial Earnings | B20: =B8-B17 -> 95000 | C20: =C8-C17 -> 269000 | D20: =D8-D17 -> 438000 | E20: =E8-E17 -> 660000 | F20: =F8-F17 -> 710000
A21: Depreciation | B21: 30000 | C21: 26000 | D21: 22000 | E21: 18000 | F21: 14000
A22: Operating Profit | B22: =B20-B21 -> 65000 | C22: =C20-C21 -> 243000 | D22: =D20-D21 -> 416000 | E22: =E20-E21 -> 642000 | F22: =F20-F21 -> 696000
A24: Interest Expense | B24: 23000 | C24: 20000 | D24: 17000 | E24: 14000 | F24: 11000
A25: Pretax Profit | B25: =B22-B24 -> 42000 | C25: =C22-C24 -> 223000 | D25: =D22-D24 -> 399000 | E25: =E22-E24 -> 628000 | F25: =F22-F24 -> 685000
A27: Tax Liability | B27: =MROUND(B25*$I$4,500) -> 13500 | C27: =MROUND(C25*$I$4,500) -> 71500 | D27: =MROUND(D25*$I$4,500) -> 127500 | E27: =MROUND(E25*$I$4,500) -> 201000 | F27: =MROUND(F25*$I$4,500) -> 219000
A28: After-Tax Profit | B28: =B25-B27 -> 28500 | C28: =C25-C27 -> 151500 | D28: =D25-D27 -> 271500 | E28: =E25-E27 -> 427000 | F28: =F25-F27 -> 466000
A30: Dividends to Shareholders | B30: 5000 | C30: 5000 | D30: 10000 | E30: 20000 | F30: 30000
A32: Retained Earnings | B32: =B28-B30 -> 23500 | C32: =C28-C30 -> 146500 | D32: =D28-D30 -> 261500 | E32: =E28-E30 -> 407000 | F32: =F28-F30 -> 436000

Sheet Cash Flow
A1: Green View Camping Supplies
A2: Cash Flow
A4: Cash Balance on Starting Date | B4: 250000
A6: Cash Inflows | B6: Year 1 | C6: Year 2 | D6: Year 3 | E6: Year 4 | F6: Year 5
A7: Operating Profit | B7: ='Income Statement'!B22 -> 65000 | C7: ='Income Statement'!C22 -> 243000 | D7: ='Income Statement'!D22 -> 416000 | E7: ='Income Statement'!E22 -> 642000 | F7: ='Income Statement'!F22 -> 696000
A8: Depreciation Add-Back | B8: ='Income Statement'!B21 -> 30000 | C8: ='Income Statement'!C21 -> 26000 | D8: ='Income Statement'!D21 -> 22000 | E8: ='Income Statement'!E21 -> 18000 | F8: ='Income Statement'!F21 -> 14000
A9: Additional Cash Received | B9: 0 | C9: 0 | D9: 0 | E9: 0 | F9: 0
A10: New Borrowing | B10: 0 | C10: 0 | D10: 0 | E10: 0 | F10: 0
A11: Sales of Other Current Assets | B11: 0 | C11: 0 | D11: 0 | E11: 0 | F11: 0
A12: TOTAL CASH INFLOW | B12: =SUM(B7:B11) -> 95000 | C12: =SUM(C7:C11) -> 269000 | D12: =SUM(D7:D11) -> 438000 | E12: =SUM(E7:E11) -> 660000 | F12: =SUM(F7:F11) -> 710000
A14: Cash Outflows | B14: Year 1 | C14: Year 2 | D14: Year 3 | E14: Year 4 | F14: Year 5
A15: Loan Payment to Investors | B15: 60000 | C15: 60000 | D15: 60000 | E15: 60000 | F15: 60000
A16: Dividends | B16: ='Income Statement'!B30 -> 5000 | C16: ='Income Statement'!C30 -> 5000 | D16: ='Income Statement'!D30 -> 10000 | E16: ='Income Statement'!E30 -> 20000 | F16: ='Income Statement'!F30 -> 30000
A17: Estimated Tax | B17: ='Income Statement'!B27 -> 13500 | C17: ='Income Statement'!C27 -> 71500 | D17: ='Income Statement'!D27 -> 127500 | E17: ='Income Statement'!E27 -> 201000 | F17: ='Income Statement'!F27 -> 219000
A18: Interest Payments | B18: ='Income Statement'!B24 -> 23000 | C18: ='Income Statement'!C24 -> 20000 | D18: ='Income Statement'!D24 -> 17000 | E18: ='Income Statement'!E24 -> 14000 | F18: ='Income Statement'!F24 -> 11000
A19: Debt Payment | B19: 72000 | C19: 76000 | D19: 80000 | E19: 84000 | F19: 88000
A20: TOTAL CASH OUTFLOW | B20: =SUM(B15:B19) -> 173500 | C20: =SUM(C15:C19) -> 232500 | D20: =SUM(D15:D19) -> 294500 | E20: =SUM(E15:E19) -> 379000 | F20: =SUM(F15:F19) -> 408000
A22: NET CASH FLOW | B22: =B12-B20 -> -78500 | C22: =C12-C20 -> 36500 | D22: =D12-D20 -> 143500 | E22: =E12-E20 -> 281000 | F22: =F12-F20 -> 302000
A23: CASH BALANCE | B23: =B4+'Cash Flow'!B22 -> 171500 | C23: =B23+C22 -> 208000 | D23: =C23+D22 -> 351500 | E23: =D23+E22 -> 632500 | F23: =E23+F22 -> 934500

Sheet Balance Sheet
A1: Green View Camping Supplies
A2: Balance Sheet
A4: Assets | B4: Year 1 | C4: Year 2 | D4: Year 3 | E4: Year 4 | F4: Year 5
A5: Current Assets
A6: Cash | B6: ='Cash Flow'!B23 -> 171500 | C6: ='Cash Flow'!C23 -> 208000 | D6: ='Cash Flow'!D23 -> 351500 | E6: ='Cash Flow'!E23 -> 632500 | F6: ='Cash Flow'!F23 -> 934500
A7: Accounts Receivable | B7: 0 | C7: 0 | D7: 0 | E7: 0 | F7: 0
A8: Inventory | B8: 0 | C8: 0 | D8: 0 | E8: 0 | F8: 0
A9: Total Current Assets | B9: =SUM(B6:B8) -> 171500 | C9: =SUM(C6:C8) -> 208000 | D9: =SUM(D6:D8) -> 351500 | E9: =SUM(E6:E8) -> 632500 | F9: =SUM(F6:F8) -> 934500
A11: Property and Equipment
A12: Property | B12: 95000 | C12: 95000 | D12: 95000 | E12: 95000 | F12: 95000
A13: Miscellaneous Assets | B13: 65000 | C13: 65000 | D13: 65000 | E13: 65000 | F13: 65000
A14: Long-Term Assets | B14: 200000 | C14: 200000 | D14: 200000 | E14: 200000 | F14: 200000
A15: Less Accumulated Depreciation | B15: =-SUM('Income Statement'!$B$21:'Income Statement'!B21) -> -30000 | C15: =-SUM('Income Statement'!$B$21:'Income Statement'!C21) -> -56000 | D15: =-SUM('Income Statement'!$B$21:'Income Statement'!D21) -> -78000 | E15: =-SUM('Income Statement'!$B$21:'Income Statement'!E21) -> -96000 | F15: =-SUM('Income Statement'!$B$21:'Income Statement'!F21) -> -110000
A16: Net Property & Equipment | B16: =SUM(B12:B15) -> 330000 | C16: =SUM(C12:C15) -> 304000 | D16: =SUM(D12:D15) -> 282000 | E16: =SUM(E12:E15) -> 264000 | F16: =SUM(F12:F15) -> 250000
A18: TOTAL ASSETS | B18: =B9+B16 -> 501500 | C18: =C9+C16 -> 512000 | D18: =D9+D16 -> 633500 | E18: =E9+E16 -> 896500 | F18: =F9+F16 -> 1184500
A20: Liabilities and Equity | B20: Year 1 | C20: Year 2 | D20: Year 3 | E20: Year 4 | F20: Year 5
A21: Current Liabilities
A22: Total Current Liabilities | B22: 0 | C22: 0 | D22: 0 | E22: 0 | F22: 0
A24: Long-Term Liabilities
A25: Total Long-Term Liabilities | B25: =420000-SUM('Cash Flow'!$B$19:'Cash Flow'!B19) -> 348000 | C25: =420000-SUM('Cash Flow'!$B$19:'Cash Flow'!C19) -> 272000 | D25: =420000-SUM('Cash Flow'!$B$19:'Cash Flow'!D19) -> 192000 | E25: =420000-SUM('Cash Flow'!$B$19:'Cash Flow'!E19) -> 108000 | F25: =420000-SUM('Cash Flow'!$B$19:'Cash Flow'!F19) -> 20000
A27: Equity
A28: Initial Investment | B28: 720000 | C28: 720000 | D28: 720000 | E28: 720000 | F28: 720000
A29: Less Start-Up Expenses | B29: -530000 | C29: -530000 | D29: -530000 | E29: -530000 | F29: -530000
A30: Less Investor Repayment | B30: =-'Cash Flow'!B15 -> -60000 | C30: =B30-'Cash Flow'!C15 -> -120000 | D30: =C30-'Cash Flow'!D15 -> -180000 | E30: =D30-'Cash Flow'!E15 -> -240000 | F30: =E30-'Cash Flow'!F15 -> -300000
A31: Accumulated Retained Earnings | B31: ='Income Statement'!B32 -> 23500 | C31: =B31+'Income Statement'!C32 -> 170000 | D31: =C31+'Income Statement'!D32 -> 431500 | E31: =D31+'Income Statement'!E32 -> 838500 | F31: =E31+'Income Statement'!F32 -> 1274500
A32: Total Equity | B32: =SUM(B28:B31) -> 153500 | C32: =SUM(C28:C31) -> 240000 | D32: =SUM(D28:D31) -> 441500 | E32: =SUM(E28:E31) -> 788500 | F32: =SUM(F28:F31) -> 1164500
A34: TOTAL LIABILITIES AND EQUITY | B34: =B22+B25+B32 -> 501500 | C34: =C22+C25+C32 -> 512000 | D34: =D22+D25+D32 -> 633500 | E34: =E22+E25+E32 -> 896500 | F34: =F22+F25+F32 -> 1184500
A36: NET WORTH | B36: =B18-B25 -> 153500 | C36: =C18-C25 -> 240000 | D36: =D18-D25 -> 441500 | E36: =E18-E25 -> 788500 | F36: =F18-F25 -> 1164500
